teste_alyson89/__init__.py
teste_alyson89/core.py
sua_lib_legal-0.1.0.dist-info/METADATA
sua_lib_legal-0.1.0.dist-info/WHEEL
sua_lib_legal-0.1.0.dist-info/top_level.txt
sua_lib_legal-0.1.0.dist-info/RECORD
