Metadata-Version: 2.4
Name: sua_lib_legal
Version: 0.1.0
Summary: Uma biblioteca Python feita com carinho
Author: Alyson
Author-email: alysonsantosalves@gmail.com
Classifier: Programming Language :: Python :: 3
Classifier: License :: OSI Approved :: MIT License
Classifier: Operating System :: OS Independent
Requires-Python: >=3.7
Dynamic: author
Dynamic: author-email
Dynamic: classifier
Dynamic: description
Dynamic: description-content-type
Dynamic: requires-python
Dynamic: summary
